[{"local_selfowned_integer": "local population", "IDP_selfowned": "IDPs", "IDP_other_integer": "IDPs", "commercial_big": "Commercial", "heavy_dmg": "Heavy Damages", "IDP_rented_integer": "IDPs", "consultation_medium": "Consultation", "location_manual": "Please enter street name and house number", "admin_q22": "Where do people go to the hospital?", "admin_q23": "Is there a pharmacy within your community (admin4)?", "admin_q20": "Out of  all amount of people under 18, what is the number of IDPs under 18?", "admin_q21": "Is there a hospital within your community (admin4)?", "admin_q24": "Where do people go to the pharmacy?", "admin_q28": "What is the number of household without gas (those who need it)?", "admin_q29": "What is the number of household without electricity?", "heavy_dmg_integer": "Heavy Damages", "admin_q24_integer": "Where do people go to the pharmacy?", "_gpslocation_altitude": "_gpslocation_altitude", "admin_q20_integer": "Out of  all amount of people under 18, what is the number of IDPs under 18?", "local_selfowned": "local population", "admin_q19_integer": "Out of  all amount of people under 18, what is the number of people under 5?", "_submission_time": "_submission_time", "_index": "_index", "admin_q17": "What is the number of people between 18 and 60?", "admin_q16": "What is the number of people over 60 years of age?", "admin_q15": "What the number of unemployed population?", "admin_q14": "What is the number of people in the area who are IDPs (Internally Displaced People)?", "admin_q13": "What is the number of people displaced by conflict who HAVE returned", "admin_q12": "What is the number of people displaced by conflict who have NOT returned?", "admin_q11": "What is a number of people with disabilities?", "admin_q10": "What is the number of  female population?", "admin_q36_integer": "How is water quality tested in the community?", "admin_q18_integer": "What is the number of people under 18?", "admin_q19": "Out of  all amount of people under 18, what is the number of people under 5?", "admin_q18": "What is the number of people under 18?", "IDP_rented": "IDPs", "admin_q3": "Which basic services are delivered WHOLLY or PARTLY by non-governmental actors?", "admin_q2": "Which basic services are delivered ENTIRELY by the Government?", "admin_q1": "Which administrative services does the community lack?", "admin_q10_integer": "What is the number of  female population?", "shelter_dmg_lived_yn": "Out of these, could you estimate the percentage of how many are currently living in their damaged home?", "admin_q5": "Is there any system or committee where people can raise the complaints regarding services such as education, health and housing?", "admin_q4": "What are the key concerns for local governance in this community?", "consultation_big": "Consultation", "admin_q9": "What is the number of male population?", "admin_q8": "What is the number of total population?", "enum_id": "Enter enumerator ID", "admin_q6_other": "IF YES, Which ones?", "admin_q7_other": "Please specify:", "shelter_dmg_lived": "Out of these, could you estimate the percentage of how many are currently living in their damaged home?", "admin_q16_integer": "What is the number of people over 60 years of age?", "admin_q12_integer": "What is the number of people displaced by conflict who have NOT returned?", "admin_q23_integer": "Is there a pharmacy within your community (admin4)?", "facility_name": "Name of Facility", "_uuid": "_uuid", "gpslocation": "I5. Record the current location", "admin_q2_other": "Please specify:", "admin_q35_integer": "What is the number of houses without access to running water in their houses?", "admin_q3_other": "Please specify:", "local_other_integer": "local population", "name_KI": "Name of Key Informant", "date_assessment": "date_assessment", "medium_dmg_integer": "Medium Damages", "admin_q22_integer": "Where do people go to the hospital?", "admin_q29_integer": "What is the number of household without electricity?", "admin_q33_integer": "How many people in the community have been hurt due to the conflict?", "financial_big": "Financial", "production_big": "Production", "_gpslocation_longitude": "_gpslocation_longitude", "current_raion": "I2. Please select current raion", "gps_work": "I4. Does the GPS work?", "admin_q14_integer": "What is the number of people in the area who are IDPs (Internally Displaced People)?", "current_village": "I3. Please select current settlement/village", "IDP_selfowned_integer": "IDPs", "informed_consent": "Greetings,\\nI am from a non-government organizational initiative called REACH. We are conducting an assessment, which involves research to understand the community needs and capacities in this area in different sectors such as Health, Education, Livelihoods. I\u2019d like to ask you some questions about  this interview should take 15-20 minutes, there are no direct benefits, compensation or risks involved for participating in this interview. All the Personally Identifiable Information will be kept confidential, and the other information will be used strictly for humanitarian purposes. \\nParticipation is voluntary, you have the right to decline to participate and to withdraw from the research once participation has begun and you may discontinue participation at any time without any penalty or loss. You may also choose to not answer/skip questions you\u2019re not comfortable with. Should you have further questions about our work, or about this assessment we will share our contact number at the end of the interview.", "production_medium": "Production", "start": "start", "commercial_small": "Commercial", "admin_q8_integer": "What is the number of total population?", "admin_q4_other": "Please specify:", "admin_q17_integer": "What is the number of people between 18 and 60?", "consultation_small": "Consultation", "light_dmg_integer": "Light Damages", "phone": "Phone number", "admin_q34_integer": "How many people in the community have been killed due to the conflict?", "admin_q13_integer": "What is the number of people displaced by conflict who HAVE returned", "production_small": "Production", "shelter_assist_need_yn": "How many HHs are currently in need of shelter assistance?", "deviceid": "deviceid", "admin_q7": "What are the three basic service sectors causing most concern in terms of delivery?", "_gpslocation_precision": "_gpslocation_precision", "admin_q15_integer": "What the number of unemployed population?", "admin_q28_integer": "What is the number of household without gas (those who need it)?", "admin_q11_integer": "What is a number of people with disabilities?", "end": "end", "KI_position": "Position", "admin_q9_integer": "What is the number of male population?", "gender_KI": "Gender", "light_dmg": "Light Damages", "current_oblast": "I1. Please select current oblast", "shelter_assist_need": "How many HHs are currently in need of shelter assistance?", "local_rented_integer": "local population", "data_sharing": "Is the KI ready to share the data now?", "_gpslocation_latitude": "_gpslocation_latitude", "commercial_medium": "Commercial", "financial_small": "Financial", "medium_dmg": "Medium Damages", "admin_q21_integer": "Is there a hospital within your community (admin4)?", "admin_q31": "What is a number of medium-size employers in the community? (Disaggregated by sector)", "admin_q30": "What is a number of small employers in the community? (Disaggregated by sector)", "admin_q33": "How many people in the community have been hurt due to the conflict?", "admin_q32": "What is a number of large employers in the community?(Disaggregated by sector)", "admin_q35": "What is the number of houses without access to running water in their houses?", "admin_q34": "How many people in the community have been killed due to the conflict?", "admin_q36": "How is water quality tested in the community?", "_id": "_id", "financial_medium": "Financial", "local_rented": "local population"}]